{
    "url": "https://torchbox.com/team/chris-lawton/",
    "id": "c0b09b2c-2157-4411",
    "title": "Chris Lawton",
    "metadata": {
        "description": "Chris is a Senior Front End Developer at Torchbox, meaning he builds digital platforms and systems that ensure a slick cross-platform user experience.",
        "twitter": {
            "card": "summary",
            "site": "@torchbox",
            "title": "Chris Lawton",
            "description": "Chris is a Senior Front End Developer at Torchbox, meaning he builds digital platforms and systems that ensure a slick cross-platform user experience."
        },
        "og": {
            "type": "website",
            "url": "/team/chris-lawton/",
            "title": "Chris Lawton",
            "description": "Chris is a Senior Front End Developer at Torchbox, meaning he builds digital platforms and systems that ensure a slick cross-platform user experience."
        }
    },
    "pageLinks": [],
    "youtubeEmbeds": []
}
